lucid_logger/__init__.py
lucid_logger/lucid_loading_bar.py
lucid_logger/lucid_logging_formaters.py
lucid_logger/lucid_logging_handlers.py
lucid_logger-0.0.6.dist-info/METADATA
lucid_logger-0.0.6.dist-info/WHEEL
lucid_logger-0.0.6.dist-info/top_level.txt
lucid_logger-0.0.6.dist-info/RECORD
